data_cleaner/__init__.py
data_cleaner/configs.py
data_cleaner/helpers.py
data_cleaner/services.py
data_cleaner/tests/__init__.py
data_cleaner/tests/test_helpers.py
data_cleaner/tests/test_services.py
reply_data_processing-0.0.9.dist-info/LICENSE
reply_data_processing-0.0.9.dist-info/METADATA
reply_data_processing-0.0.9.dist-info/WHEEL
reply_data_processing-0.0.9.dist-info/top_level.txt
reply_data_processing-0.0.9.dist-info/RECORD
