Metadata-Version: 2.1
Name: reply-data-processing
Version: 0.0.9
Summary: Package for processing data in multiple formats for Reply AI services
Home-page: https://github.com/reply-team/reply_ai_data_processing
Author: Marianna Diachuk
Author-email: marianna.d@reply.io
Project-URL: Bug Tracker, https://github.com/reply-team/reply_ai_data_processing
Classifier: Programming Language :: Python :: 3
Classifier: License :: OSI Approved :: MIT License
Classifier: Operating System :: OS Independent
Requires-Python: >=3.7
License-File: LICENSE
